cointsmall/__init__.py
cointsmall/adf_test.py
cointsmall/cointegration_test.py
cointsmall/composite_test.py
cointsmall/critical_values.py
cointsmall/verify.py
cointsmall-0.1.0.dist-info/licenses/LICENSE
cointsmall-0.1.0.dist-info/METADATA
cointsmall-0.1.0.dist-info/WHEEL
cointsmall-0.1.0.dist-info/top_level.txt
cointsmall-0.1.0.dist-info/RECORD
