Metadata-Version: 2.4
Name: cointsmall
Version: 0.1.0
Summary: Cointegration testing with structural breaks in very small samples (Python port of R package by Dr. Merwan Roudane, Independent Researcher)
Home-page: https://github.com/yourusername/cointsmall-python
Author: Jérôme Trinh (methodology), Dr. Merwan Roudane (R package), Python port
Author-email: merwanroudane920@gmail.com
Maintainer: Dr. Merwan Roudane
Maintainer-email: merwanroudane920@gmail.com
Classifier: Development Status :: 3 - Alpha
Classifier: Intended Audience :: Science/Research
Classifier: Topic :: Scientific/Engineering :: Mathematics
Classifier: License :: OSI Approved :: GNU General Public License v3 (GPLv3)
Classifier: Programming Language :: Python :: 3
Classifier: Programming Language :: Python :: 3.7
Classifier: Programming Language :: Python :: 3.8
Classifier: Programming Language :: Python :: 3.9
Classifier: Programming Language :: Python :: 3.10
Classifier: Programming Language :: Python :: 3.11
Requires-Python: >=3.7
License-File: LICENSE
Requires-Dist: numpy>=1.19.0
Requires-Dist: scipy>=1.5.0
Requires-Dist: statsmodels>=0.12.0
Requires-Dist: pandas>=1.1.0
Provides-Extra: dev
Requires-Dist: pytest>=6.0; extra == "dev"
Requires-Dist: pytest-cov>=2.10; extra == "dev"
Dynamic: author
Dynamic: author-email
Dynamic: classifier
Dynamic: description
Dynamic: description-content-type
Dynamic: home-page
Dynamic: license-file
Dynamic: maintainer
Dynamic: maintainer-email
Dynamic: provides-extra
Dynamic: requires-dist
Dynamic: requires-python
Dynamic: summary
